Metadata-Version: 2.1
Name: pystatworld
Version: 0.1.0
Summary: Calculate and visuallize, Gaussian, Binomial and Normal distributions
Home-page: UNKNOWN
Author-email: ai.sumitsagar@gmail.com
License: UNKNOWN
Platform: UNKNOWN
